ve_lance_sdk-0.24.105.dist-info/METADATA
ve_lance_sdk-0.24.105.dist-info/WHEEL
ve_lance_sdk-0.24.105.dist-info/licenses/LICENSE
lance.libs/libcrypto-ce0fec9c.so.1.1
lance.libs/libssl-aaaf241b.so.1.1
lance/_dataset/cache.py
lance/_dataset/__init__.py
lance/_dataset/sharded_batch_iterator.py
lance/tag.py
lance/blob.py
lance/conftest.py
lance/debug.py
lance/dataset.py
lance/log.py
lance/download.py
lance/progress.py
lance/lance/trace.pyi
lance/lance/schema.pyi
lance/lance/optimize.pyi
lance/lance/__init__.pyi
lance/lance/datagen/__init__.pyi
lance/lance/debug.pyi
lance/lance/fragment.pyi
lance/lance/indices/__init__.pyi
lance/util.py
lance/indices.py
lance/schema.py
lance/hf.py
lance/_arrow/bf16.py
lance/_arrow/__init__.py
lance/torch/async_dataset.py
lance/torch/bench_utils.py
lance/torch/dist.py
lance/torch/data.py
lance/torch/kmeans.py
lance/torch/__init__.py
lance/torch/distance.py
lance/arrow.py
lance/tf/tfrecord.py
lance/tf/data.py
lance/tf/__init__.py
lance/dependencies.py
lance/catalog/catalog.py
lance/catalog/las_catalog.py
lance/catalog/dummy_catalog.py
lance/catalog/hive_catalog.py
lance/catalog/exceptions.py
lance/catalog/__init__.py
lance/catalog/utils.py
lance/udf.py
lance/vector.py
lance/types.py
lance/commit.py
lance/sampler.py
lance/ray/sink.py
lance/ray/__init__.py
lance/file.py
lance/tracing.py
lance/optimize.py
lance/_datagen.py
lance/fragment.py
lance/__init__.py
lance/lance.abi3.so
ve_lance_sdk-0.24.105.dist-info/RECORD
