Metadata-Version: 2.4
Name: ve-lance-sdk
Version: 0.24.105
Classifier: Development Status :: 3 - Alpha
Classifier: Environment :: Console
Classifier: Intended Audience :: Science/Research
Classifier: License :: OSI Approved :: Apache Software License
Classifier: Operating System :: OS Independent
Classifier: Programming Language :: Python
Classifier: Programming Language :: Python :: 3
Classifier: Programming Language :: Python :: 3 :: Only
Classifier: Programming Language :: Python :: 3.9
Classifier: Programming Language :: Python :: 3.10
Classifier: Programming Language :: Python :: 3.11
Classifier: Programming Language :: Python :: 3.12
Classifier: Programming Language :: Rust
Classifier: Topic :: Scientific/Engineering
Requires-Dist: pyarrow>=14
Requires-Dist: numpy>=1.22
Requires-Dist: volcengine>=1.0.154,<2
Requires-Dist: ve-lascatalog-sdk>=1.0.0,<2
Requires-Dist: hive-metastore-client>=1.0.9
Requires-Dist: boto3 ; extra == 'tests'
Requires-Dist: datasets ; extra == 'tests'
Requires-Dist: duckdb ; extra == 'tests'
Requires-Dist: ml-dtypes ; extra == 'tests'
Requires-Dist: pillow ; extra == 'tests'
Requires-Dist: pandas ; extra == 'tests'
Requires-Dist: polars[pyarrow,pandas] ; extra == 'tests'
Requires-Dist: pytest ; extra == 'tests'
Requires-Dist: tensorflow ; extra == 'tests'
Requires-Dist: tqdm ; extra == 'tests'
Requires-Dist: ruff==0.4.1 ; extra == 'dev'
Requires-Dist: pyright ; extra == 'dev'
Requires-Dist: pytest-benchmark ; extra == 'benchmarks'
Requires-Dist: torch ; extra == 'torch'
Requires-Dist: ray[data]<2.38 ; python_full_version < '3.12' and extra == 'ray'
Provides-Extra: tests
Provides-Extra: dev
Provides-Extra: benchmarks
Provides-Extra: torch
Provides-Extra: ray
License-File: LICENSE
Summary: python wrapper for Lance columnar format
Keywords: data-format,data-science,machine-learning,arrow,data-analytics
Author: Lance Devs <dev@lancedb.com>
Author-email: Lance Devs <dev@lancedb.com>
Requires-Python: >=3.9
